Workbook

Sheet Risk Register
A1: NORTHLINK COMMUNICATIONS — CYBER RISK REGISTER
A2: Prepared by: Kapil Chaudhary | Framework: ISO 27001:2022 | Version: 1.1 | Last Reviewed: June 2025
A3: Risk ID | B3: Risk Category | C3: Risk Description | D3: Affected Asset | E3: Department | F3: Risk Owner | G3: Likelihood (1-5) | H3: Impact (1-5) | I3: Risk Score (LxI) | J3: Risk Rating | K3: Existing Controls | L3: Treatment | M3: Recommended Action | N3: Status
A4: RISK-001 | B4: Access Control | C4: Unauthorized access to satellite network management console due to shared admin credentials and no MFA enforcement. | D4: Network Management System | E4: IT / NOC | F4: NOC Manager | G4: 4 | H4: 5 | I4: =G4*H4 -> 20 | J4: Critical | K4: Basic password policy exists; no MFA deployed on management console. | L4: Mitigate | M4: Enforce MFA on all privileged accounts. Implement individual admin accounts. Review access quarterly. Aligns with ISO 27001 A.9.4.2. | N4: Open
A5: RISK-002 | B5: Malware & Ransomware | C5: Remote satellite sites running outdated firmware on Fortinet devices, increasing exposure to known CVEs and ransomware. | D5: Fortinet Firewalls (145 sites) | E5: IT / NOC | F5: Network Engineer | G5: 4 | H5: 4 | I5: =G5*H5 -> 16 | J5: Critical | K5: Patch cycle exists but is informal; no automated patching. Some sites on firmware 6.x. | L5: Mitigate | M5: Establish formal patch management policy. Schedule quarterly firmware updates. Track patch compliance per site. Aligns with ISO 27001 A.12.6.1. | N5: In Progress
A6: RISK-003 | B6: Third-Party Risk | C6: Satellite equipment vendors have broad remote access to site hardware with no formal third-party access agreement or monitoring. | D6: Remote Site Hardware | E6: Operations | F6: Vendor Manager | G6: 3 | H6: 5 | I6: =G6*H6 -> 15 | J6: Critical | K6: Vendor contracts exist. No third-party access log or formal SLA for security controls. | L6: Mitigate | M6: Implement vendor access agreements with security requirements. Log all third-party sessions. Conduct annual vendor risk assessments. Aligns with ISO 27001 A.15.1. | N6: Open
A7: RISK-004 | B7: Data Breach / Privacy | C7: Customer PII and billing data stored in on-premise database with no encryption at rest and minimal access controls. | D7: Customer Database | E7: Finance | F7: IT Manager | G7: 3 | H7: 5 | I7: =G7*H7 -> 15 | J7: Critical | K7: Database is behind firewall. No encryption at rest. Access not reviewed in 12+ months. | L7: Mitigate | M7: Encrypt database at rest using AES-256. Implement role-based access control. Conduct quarterly access reviews. Aligns with ISO 27001 A.10.1, A.9.2. | N7: Open
A8: RISK-005 | B8: Social Engineering | C8: NOC staff and field technicians lack formal security awareness training, increasing phishing and social engineering susceptibility. | D8: All Employees | E8: All Departments | F8: HR / Security Lead | G8: 4 | H8: 3 | I8: =G8*H8 -> 12 | J8: High | K8: No formal training program. Ad-hoc awareness emails sent occasionally. | L8: Mitigate | M8: Deploy annual security awareness training. Run quarterly phishing simulations. Track completion rates. Aligns with ISO 27001 A.7.2.2. | N8: Open
A9: RISK-006 | B9: Physical Security | C9: Remote satellite sites in northern/rural locations have no CCTV, minimal physical barriers, and no intrusion detection. | D9: Remote Site Physical Infrastructure | E9: Operations | F9: Site Operations Manager | G9: 2 | H9: 4 | I9: =G9*H9 -> 8 | J9: Medium | K9: Sites are fenced. No cameras or intrusion alarms. Physical access logs not maintained. | L9: Accept | M9: Document accepted risk with business justification. Review annually. Consider CCTV for highest-risk sites. Aligns with ISO 27001 A.11.1. | N9: Under Review
A10: RISK-007 | B10: Business Continuity | C10: No documented disaster recovery or business continuity plan exists for core NOC operations in event of major outage or incident. | D10: NOC Operations | E10: IT | F10: CTO | G10: 3 | H10: 5 | I10: =G10*H10 -> 15 | J10: Critical | K10: Informal runbooks exist. No formal BCP/DRP tested or documented. | L10: Mitigate | M10: Develop and document BCP and DRP. Conduct tabletop exercise annually. Define RTO/RPO targets. Aligns with ISO 27001 A.17.1. | N10: Open
A11: RISK-008 | B11: Insider Threat | C11: Terminated employee accounts not disabled promptly; access reviews show 3 former staff with active VPN credentials. | D11: VPN / Remote Access | E11: IT | F11: HR Manager | G11: 3 | H11: 4 | I11: =G11*H11 -> 12 | J11: High | K11: Offboarding checklist exists but not consistently followed. No automated deprovisioning. | L11: Mitigate | M11: Implement automated account deprovisioning on termination. Conduct monthly access review. Tie offboarding to HR system. Aligns with ISO 27001 A.9.2.6. | N11: In Progress
A12: RISK-009 | B12: Cloud Misconfiguration | C12: AWS S3 buckets used for log archival are publicly accessible due to misconfigured bucket policies. | D12: AWS Cloud Infrastructure | E12: IT | F12: Cloud Administrator | G12: 2 | H12: 4 | I12: =G12*H12 -> 8 | J12: Medium | K12: Cloud environment in use. No CSPM tool deployed. Manual review only. | L12: Mitigate | M12: Remediate S3 bucket permissions immediately. Deploy Cloud Security Posture Management (CSPM). Set SCPs to block public bucket creation. Aligns with ISO 27001 A.13.1. | N12: Open
A13: RISK-010 | B13: Cryptographic Controls | C13: SSL certificates for customer portal and internal tools use SHA-1 and are approaching expiry with no automated renewal process. | D13: Customer Web Portal | E13: IT | F13: Web Administrator | G13: 3 | H13: 3 | I13: =G13*H13 -> 9 | J13: Medium | K13: Certificates manually tracked in a spreadsheet. No automated expiry alerts. | L13: Mitigate | M13: Migrate all certificates to SHA-256 or higher. Implement automated certificate lifecycle management. Set 60-day expiry alerts. Aligns with ISO 27001 A.10.1.1. | N13: In Progress
A14: RISK-011 | B14: Information Security — Data Classification | C14: NOC engineer inadvertently shared network topology diagrams including all site IP ranges in an external Slack channel with a third-party vendor. No data classification policy or DLP tool exists. | D14: Network Architecture Documentation | E14: IT / NOC | F14: NOC Manager | G14: 3 | H14: 4 | I14: =G14*H14 -> 12 | J14: High | K14: Slack audit logs available. No formal data classification policy or DLP in place. | L14: Mitigate | M14: Develop and publish a Data Classification Policy defining Confidential, Internal, and Public tiers. Deliver targeted awareness training for NOC staff. Deploy DLP solution for collaboration tools. Aligns with ISO 27001 A.8.2, A.7.2.2. | N14: Open
A15: RISK-012 | B15: Operations Security | C15: Legacy billing system running on end-of-life Windows Server 2012 R2 with no security patches since October 2023. System processes customer billing and stores credit card data. Migration delayed due to budget constraints. No compensating controls formally documented. | D15: Billing System / Customer Payment Data | E15: Finance | F15: IT Manager | G15: 5 | H15: 5 | I15: 25 | J15: Critical | K15: System Isolated from main network. Access restricted to VPN only. No formal documentation of compensating controls. | L15: Mitigate | M15: Obtain formal signed risk acceptance from leadership with migration deadline commitment. Develop legacy system decommsion plan with budget approval. Enable enhance logging and alerting on isolated system. Train staff to access only via VPN and only when necessary. Aligns with ISO 270001 A.12.6.1,A18.1.4 | N15: Open
A16: RISK-013 | B16: Access Control | C16: NOC technician promoted to IT Admin role retains full NOC credentials in addition to new privileges. No formal access review process exists for internal role changes. Employee has unauthorized access to the systems outside current job scope - a case of privilege accumulation. | D16: NOC System / Network Infrastructure | E16: IT | F16: IT Manager | G16: 3 | H16: 4 | I16: 12 | J16: High | K16: Centralized Audit logging in place. No automated alerting on anamalous access. No formal role-change access review process. | L16: Mitigate | M16: Immediately revoke legacy NOC credentials for affected employee. Implement formal review process triggered by any role change or internal transfer. Conduct quaterly access recertification across all staff. Introduce principle of least privilege policy. Aligns with ISO 27001 A.9.2.2, A.9.2.5 | N16: Open
A17: RISK-014 | B17: Third-Party Risk / Supplier Risk | C17: Cloud Payroll vendor PayFlow Pro stores employees SIN numbers,salary details, and banking information in plain text. NorthLink has no visibility into vendor security controls, no SOC2 report on file, and vendor contract contains no security requirements clause. | D17: Employee Payroll Data / HR Systems | E17: HR | F17: HR Manager | G17: 5 | H17: 5 | I17: 25 | J17: Critical | K17: Verbal agreement with vendor regarding data responsibility. No formal DPA in place. No security requirements in contract. No SOC 2 report requested or reviewed. | L17: Mitigate | M17: Immediately demand PayFlow Pro encrypt all data at rest within 30 days or suspend contract. Execute a formal Data Processing Agreement specifying encryption, access controls, and breach notification obligations. Request current SOC 2 Type II report. Implement annual vendor risk assessment process for all vendors handling sensitive data. Aligns with ISO 27001 A.15.2,A.15.2.1. PIPEDA breach notifications obligations noted. | N17: Open
A18: RISK-015 | B18: Operations Security | C18: Enterprise VPN solution used by 45 remote employees including NOC engineers contains a critical unpatched vulnerability with a publicly available exploit (CVE published 6 months ago, patch available 5 months ago). Successful exploitation could grant attacker access to all 145 satellite sites via lateral movement through NOC engineer credentials. | D18: VPN Infrastructure / Remote Access | E18: IT / NOC | F18: IT Manager | G18: 5 | H18: 5 | I18: 25 | J18: Critical | K18: VPN access restricted to company-issued devices. Enterprise-grade VPN vendor in use. Critical patch available but unapplied for 5 months. No formal vulnerability management or patch prioritization process documented. | L18: Mitigate | M18: Apply critical VPN patch on an emergency basis within 48 hours. Restrict VPN access to essential personnel only until patch is deployed. Implement formal vulnerabilty management policy with defined SLA's - critical CVEs patched within 72 hours, high within 30 days. Subscribe to vendor security advisories for proactive notification. Aligns with ISO 27001 A.12.6.1. | N18: Open
A19: RISK-016 | B19: Incident Management | C19: A phishing-related email account compromise occurred 3 months ago and was contained within 4 hours, but no formal Incident Response Plan exists at NorthLink. Response was improvised by IT Manager. No root cause analysis, incident report, or lessons-learned review was conducted following the event. | D19: Incident Response Process / Email Systems | E19: IT | F19: IT Manager | G19: 5 | H19: 4 | I19: 20 | J19: Critical | K19: SIEM tool in place for anomaly detection. No documented Incident Response Plan. No formal post-incident review process. | L19: Mitigate | M19: Conduct retrospective RCA on the prior phishing incident and document lessons learned. Develop and formally document an Incident Response Plan covering detection, containment, eradication, recovery, and post-incident review. Conduct a tabletop exercise to validate the plan. Aligns with ISO 27001 A.16.1.1, A.16.1.6. | N19: Open
A20: RISK-017 | B20: Access Control | C20: NorthLink's password policy requires only 6 characters with no complexity requirements, no expiration, and no reuse restrictions. Internal review found 30% of employees using passwords found in public breach databases. No organization-wide password manager provided. MFA enforced only on select systems. | D20: Identity & Access Management Systems | E20: IT | F20: IT Manager | G20: 5 | H20: 5 | I20: 25 | J20: Critical | K20: VPN required for remote access but does not compensate for weak credential strength. No password manager provided. MFA enforced only on select systems, not organization-wide. | L20: Mitigate | M20: Update password policy to minimum 10–12 characters with complexity requirements. Force organization-wide password reset under new policy. Enforce MFA across all systems, not just select ones. Procure and deploy an enterprise password manager (e.g., Bitwarden, Keeper) to reduce local credential storage and reuse. Aligns with ISO 27001 A.9.4.3, A.9.4.2. Credential stuffing risk noted given confirmed breach-database password matches. | N20: Open
A21: RISK-018 | B21: Operations Security | C21: Security logs across firewalls, VPN, and network management console retained for only 14 days before automatic overwrite. No centralized log aggregation — logs stored locally across 145 satellite sites. No active log review process exists. Multiple site devices found with logging disabled entirely due to uncorrected default configuration. | D21: Logging & Monitoring Infrastructure | E21: IT / NOC | F21: IT Manager | G21: 5 | H21: 5 | I21: 25 | J21: Critical | K21: Logs generated locally at most sites with 14-day retention. No centralized aggregation or SIEM correlation across sites. No active log review process. Logging confirmed disabled at multiple sites. | L21: Mitigate | M21: Immediately enable logging at all sites where it is currently disabled. Deploy centralized log aggregation into a SIEM platform for cross-site correlation and active monitoring. Extend retention to a minimum of 90 days, aligned to compliance and forensic requirements. Establish a routine log review cadence, not just incident-triggered review. Aligns with ISO 27001 A.12.4.1, A.12.4.3. | N21: Open
A22: RISK-019 | B22: Mobile Device Management / BYOD | C22: NorthLink permits BYOD access to corporate email, Slack, and internal documentation with no Mobile Device Management solution in place. Cannot enforce screen lock, remotely wipe lost devices, verify OS compliance, or separate corporate from personal data. Three employees have reported lost or stolen phones in the past year with no confirmation of data wipe status. | D22: Corporate Data on Personal Mobile Devices | E22: IT | F22: IT Manager | G22: 5 | H22: 5 | I22: 25 | J22: Critical | K22: Manual record maintained of devices granted access to corporate resources. No technical enforcement — no remote wipe, no screen lock enforcement, no OS compliance verification, no corporate/personal data separation. | L22: Mitigate | M22: Develop and publish a formal BYOD policy defining minimum security requirements prior to granting access. Deploy a Mobile Device Management solution (e.g., Microsoft Intune) to enforce policy, enable remote wipe, and verify compliance. Conduct retrospective risk assessment on the three previously reported lost/stolen devices. Aligns with ISO 27001 A.6.2.1, A.6.2.2. | N22: Open
A23: RISK-020 | B23: Compliance | C23: NorthLink has never undergone a formal ISO 27001 audit, internal or external. No designated compliance owner exists — the CTO manages security informally alongside operational duties with no dedicated budget or time allocated. No systematic verification of control implementation has occurred. A potential client recently requested proof of security certification during contract negotiation, which NorthLink could not provide. | D23: Organizational Compliance Posture | E23: Executive | F23: CTO | G23: 5 | H23: 5 | I23: 25 | J23: Critical | K23: Internal security team conducts informal yearly security posture review. No formal audit (internal or external) has ever been conducted. No designated compliance owner or allocated budget for compliance activities. | L23: Mitigate | M23: Appoint a designated compliance owner with defined responsibility and allocated budget. Conduct an internal ISO 27001 gap assessment to determine current control implementation status. Remediate highest-priority gaps identified. Engage an external auditor for formal certification once internal readiness is confirmed. Aligns with ISO 27001 A.18.2.1, A.18.2.2. | N23: Open

Sheet Risk Summary
A1: NORTHLINK COMMUNICATIONS — RISK SUMMARY
A2: Auto-calculated from Risk Register sheet. Import this file into Power BI for dashboard build.
A4: Rating | B4: Total Count | C4: % of Total | D4: Open Count | E4: In Progress | F4: Avg Risk Score
A5: Critical | B5: =COUNTIF('Risk Register'!J:J,A5) -> 13 | C5: =IF(B5=0,0,B5/SUM($B$5:$B$8)) -> 0.65 | D5: =COUNTIFS('Risk Register'!J:J,A5,'Risk Register'!N:N,"Open") -> 12 | E5: =COUNTIFS('Risk Register'!J:J,A5,'Risk Register'!N:N,"In Progress") -> 1 | F5: =IFERROR(AVERAGEIF('Risk Register'!J:J,A5,'Risk Register'!I:I),0) -> 21.230769
A6: High | B6: =COUNTIF('Risk Register'!J:J,A6) -> 4 | C6: =IF(B6=0,0,B6/SUM($B$5:$B$8)) -> 0.2 | D6: =COUNTIFS('Risk Register'!J:J,A6,'Risk Register'!N:N,"Open") -> 3 | E6: =COUNTIFS('Risk Register'!J:J,A6,'Risk Register'!N:N,"In Progress") -> 1 | F6: =IFERROR(AVERAGEIF('Risk Register'!J:J,A6,'Risk Register'!I:I),0) -> 12
A7: Medium | B7: =COUNTIF('Risk Register'!J:J,A7) -> 3 | C7: =IF(B7=0,0,B7/SUM($B$5:$B$8)) -> 0.15 | D7: =COUNTIFS('Risk Register'!J:J,A7,'Risk Register'!N:N,"Open") -> 1 | E7: =COUNTIFS('Risk Register'!J:J,A7,'Risk Register'!N:N,"In Progress") -> 1 | F7: =IFERROR(AVERAGEIF('Risk Register'!J:J,A7,'Risk Register'!I:I),0) -> 8.3333333
A8: Low | B8: =COUNTIF('Risk Register'!J:J,A8) -> 0 | C8: =IF(B8=0,0,B8/SUM($B$5:$B$8)) -> 0 | D8: =COUNTIFS('Risk Register'!J:J,A8,'Risk Register'!N:N,"Open") -> 0 | E8: =COUNTIFS('Risk Register'!J:J,A8,'Risk Register'!N:N,"In Progress") -> 0 | F8: =IFERROR(AVERAGEIF('Risk Register'!J:J,A8,'Risk Register'!I:I),0) -> 0
A9: TOTAL | B9: =SUM(B5:B8) -> 20 | C9: =SUM(C5:C8) -> 1 | D9: =SUM(D5:D8) -> 16 | E9: =SUM(E5:E8) -> 3 | F9: =IFERROR(AVERAGEIF('Risk Register'!J:J,"<>"&"",'Risk Register'!I:I),0) -> 17.45
